LICENSE
README.md
setup.cfg
setup.py
astroIm/__init__.py
astroIm/astroIm.py
astroIm/kernelCreator.py
astroIm/ppmapCube.py
astroIm/psds.py
astroIm.egg-info/PKG-INFO
astroIm.egg-info/SOURCES.txt
astroIm.egg-info/dependency_links.txt
astroIm.egg-info/requires.txt
astroIm.egg-info/top_level.txt