Metadata-Version: 2.1
Name: astroIm
Version: 0.8
Summary: Astropy Wrapper and specialised functions for FIR/Submm Astro Images
Home-page: https://github.com/mwls/astroIm
Download-URL: https://github.com/mwls/astroIm/archive/refs/tags/v_06.tar.gz
Author: Matthew Smith
Author-email: Matthew.Smith@astro.cf.ac.uk
License: MIT
Keywords: Astronomy,Image,Analysis
Classifier: Development Status :: 3 - Alpha
Classifier: Intended Audience :: Developers
Classifier: Topic :: Scientific/Engineering :: Astronomy
Classifier: License :: OSI Approved :: MIT License
Classifier: Programming Language :: Python :: 3
License-File: LICENSE
Requires-Dist: numpy>=1.19.0
Requires-Dist: astropy>=4.3
Requires-Dist: reproject>=0.7.0
Requires-Dist: photutils>=1.0.0
Requires-Dist: scipy>=1.2.0
Requires-Dist: aplpy>=2.0.0
Requires-Dist: matplotlib>=3.1.1
